langgraph_lite_cron/__init__.py
langgraph_lite_cron/crons.py
langgraph_lite_cron/shcemas.py
langgraph_lite_cron/utils.py
langgraph_lite_cron/scheduler/__init__.py
langgraph_lite_cron/scheduler/models.py
langgraph_lite_cron/scheduler/tasks.py
langgraph_lite_cron/scheduler/utils.py
langgraph_lite_cron/scheduler/datastores/__init__.py
langgraph_lite_cron/scheduler/datastores/memory.py
langgraph_lite_cron/scheduler/datastores/sqlalchemy.py
langgraph_lite_cron-0.0.3.dist-info/METADATA
langgraph_lite_cron-0.0.3.dist-info/WHEEL
langgraph_lite_cron-0.0.3.dist-info/RECORD
