Metadata-Version: 2.4
Name: langgraph-lite-cron
Version: 0.0.3
Summary: langgraph lite cron
Project-URL: Repository, https://github.com/ykoh42/langgraph-lite-cron
Project-URL: Issues, https://github.com/ykoh42/langgraph-lite-cron/issues
Author: ykoh42
License: MIT
Keywords: agent,ambient,cron,langgraph,scheduler
Requires-Python: >=3.9
Requires-Dist: apscheduler==4.0.0a6
Requires-Dist: asyncpg>=0.30.0
Requires-Dist: cbor2>=5.6.5
Requires-Dist: fastapi>=0.116.1
Requires-Dist: greenlet>=3.2.4
Requires-Dist: langgraph-sdk>=0.2.0
Requires-Dist: psycopg2-binary>=2.9.10
Requires-Dist: redis>=6.4.0
Requires-Dist: sqlalchemy>=2.0.42
Requires-Dist: tzdata>=2025.2
